retinafacex/__init__.py
retinafacex/common.py
retinafacex/constants.py
retinafacex/log.py
retinafacex/model_store.py
retinafacex/retinaface.py
retinafacex/version.py
retinafacex/visualization.py
retinafacex-0.1.2.dist-info/LICENSE
retinafacex-0.1.2.dist-info/METADATA
retinafacex-0.1.2.dist-info/WHEEL
retinafacex-0.1.2.dist-info/top_level.txt
retinafacex-0.1.2.dist-info/RECORD
