Metadata-Version: 2.1
Name: retinafacex
Version: 0.1.2
Summary: RetinaFaceX (X-extended): Lightweight Face Detection Library
Home-page: https://github.com/yakhyo/retinafacex
Author: Yakhyokhuja Valikhujaev
Author-email: yakhyo9696@gmail.com
License: MIT
Keywords: retinaface,face detection,deep learning,onnx,opencv
Classifier: Programming Language :: Python :: 3
Classifier: Programming Language :: Python :: 3.8
Classifier: Programming Language :: Python :: 3.9
Classifier: Programming Language :: Python :: 3.10
Classifier: License :: OSI Approved :: MIT License
Classifier: Operating System :: OS Independent
Classifier: Topic :: Software Development :: Libraries :: Python Modules
Requires-Python: >=3.8
License-File: LICENSE
Requires-Dist: numpy
Requires-Dist: opencv-python
Requires-Dist: onnx
Requires-Dist: onnxruntime
Requires-Dist: requests
Requires-Dist: torch
Provides-Extra: dev
Requires-Dist: pytest ; extra == 'dev'
